rtl/empty_logic.v
module empty_logic #(
    parameter ADDR_WIDTH = 4
)(
    input  [ADDR_WIDTH:0] count,

    output empty
);

assign empty = (count == 0);

endmodule

rtl/full_logic.v
module full_logic #(
    parameter DEPTH = 16,
    parameter ADDR_WIDTH = 4
)(
    input  [ADDR_WIDTH:0] count,

    output full
);

assign full = (count == DEPTH);

endmodule

rtl/read_control.v
module read_control(
    input  rd_en,
    input  empty,

    output read_enable
);

assign read_enable = rd_en && !empty;

endmodule

rtl/write_control.v
module write_control(
    input  wr_en,
    input  full,

    output write_enable
);

assign write_enable = wr_en && !full;

endmodule

rtl/fifo_counter.v
module fifo_counter #(
    parameter DEPTH = 16,
    parameter ADDR_WIDTH = 4
)(
    input                   clk,
    input                   rst,
    input                   wr_en,
    input                   rd_en,
    input                   full,
    input                   empty,

    output reg [ADDR_WIDTH:0] count
);

always @(posedge clk or posedge rst)
begin
    if (rst)
        count <= 0;

    else
    begin
        case ({wr_en && !full, rd_en && !empty})

            2'b10:
                count <= count + 1;

            2'b01:
                count <= count - 1;

            2'b11:
                count <= count;

            default:
                count <= count;

        endcase
    end
end

endmodule

rtl/read_pointer.v
`timescale 1ns/1ps
module read_pointer #(
    parameter ADDR_WIDTH = 4,
    parameter DEPTH = 16
)(
    input                       clk,
    input                       rst,
    input                       rd_en,
    input                       empty,

    output reg [ADDR_WIDTH-1:0] rd_ptr
);

localparam [ADDR_WIDTH-1:0] LAST_ADDR = {ADDR_WIDTH{1'b1}};

always @(posedge clk or posedge rst)
begin
    if (rst)
        rd_ptr <= 0;
    else if (rd_en && !empty)
    begin
        if (rd_ptr == LAST_ADDR)
            rd_ptr <= 0;
        else
            rd_ptr <= rd_ptr + 1;
    end
end

endmodule

rtl/write_pointer.v
`timescale 1ns/1ps
module write_pointer #(
    parameter ADDR_WIDTH = 4,
    parameter DEPTH = 16
)(
    input                       clk,
    input                       rst,
    input                       wr_en,
    input                       full,

    output reg [ADDR_WIDTH-1:0] wr_ptr
);

localparam [ADDR_WIDTH-1:0] LAST_ADDR = {ADDR_WIDTH{1'b1}};

always @(posedge clk or posedge rst)
begin
    if (rst)
        wr_ptr <= 0;
    else if (wr_en && !full)
    begin
        if (wr_ptr == LAST_ADDR)
            wr_ptr <= 0;
        else
            wr_ptr <= wr_ptr + 1;
    end
end

endmodule

rtl/fifo_memory.v
`timescale 1ns/1ps
module fifo_memory #(
    parameter DATA_WIDTH = 8,
    parameter DEPTH = 16,
    parameter ADDR_WIDTH = 4
)(
    input                           clk,
    input                           wr_en,
    input                           rd_en,

    input  [DATA_WIDTH-1:0]         wr_data,

    input  [ADDR_WIDTH-1:0]         wr_ptr,
    input  [ADDR_WIDTH-1:0]         rd_ptr,

    output reg [DATA_WIDTH-1:0]     rd_data
);

reg [DATA_WIDTH-1:0] mem [0:DEPTH-1];

always @(posedge clk)
begin
    if (wr_en)
        mem[wr_ptr] <= wr_data;
end

always @(posedge clk)
begin
    if (rd_en)
        rd_data <= mem[rd_ptr];
end

endmodule

rtl/fifo_top.v
`timescale 1ns/1ps
module fifo_top #(
    parameter DATA_WIDTH = 8,
    parameter DEPTH = 16,
    parameter ADDR_WIDTH = 4
)(
    input                       clk,
    input                       rst,
    input                       wr_en,
    input                       rd_en,
    input  [DATA_WIDTH-1:0]     wr_data,

    output [DATA_WIDTH-1:0]     rd_data,
    output                      full,
    output                      empty
);

wire [ADDR_WIDTH-1:0] wr_ptr;
wire [ADDR_WIDTH-1:0] rd_ptr;

wire [ADDR_WIDTH:0] count;

wire write_enable;
wire read_enable;

fifo_memory #(
    .DATA_WIDTH(DATA_WIDTH),
    .DEPTH(DEPTH),
    .ADDR_WIDTH(ADDR_WIDTH)
) u_fifo_memory (
    .clk(clk),
    .wr_en(write_enable),
    .rd_en(read_enable),
    .wr_data(wr_data),
    .wr_ptr(wr_ptr),
    .rd_ptr(rd_ptr),
    .rd_data(rd_data)
);

write_pointer #(
    .ADDR_WIDTH(ADDR_WIDTH),
    .DEPTH(DEPTH)
) u_write_pointer (
    .clk(clk),
    .rst(rst),
    .wr_en(write_enable),
    .full(full),
    .wr_ptr(wr_ptr)
);

read_pointer #(
    .ADDR_WIDTH(ADDR_WIDTH),
    .DEPTH(DEPTH)
) u_read_pointer (
    .clk(clk),
    .rst(rst),
    .rd_en(read_enable),
    .empty(empty),
    .rd_ptr(rd_ptr)
);

fifo_counter #(
    .DEPTH(DEPTH),
    .ADDR_WIDTH(ADDR_WIDTH)
) u_fifo_counter (
    .clk(clk),
    .rst(rst),
    .wr_en(wr_en),
    .rd_en(rd_en),
    .full(full),
    .empty(empty),
    .count(count)
);

write_control u_write_control (
    .wr_en(wr_en),
    .full(full),
    .write_enable(write_enable)
);

read_control u_read_control (
    .rd_en(rd_en),
    .empty(empty),
    .read_enable(read_enable)
);

full_logic #(
    .DEPTH(DEPTH),
    .ADDR_WIDTH(ADDR_WIDTH)
) u_full_logic (
    .count(count),
    .full(full)
);

empty_logic #(
    .ADDR_WIDTH(ADDR_WIDTH)
) u_empty_logic (
    .count(count),
    .empty(empty)
);

endmodule

tb/fifo_tb.v
`timescale 1ns/1ps

module fifo_tb;

parameter DATA_WIDTH = 8;
parameter DEPTH = 16;
parameter ADDR_WIDTH = 4;

reg clk;
reg rst;
reg wr_en;
reg rd_en;
reg [DATA_WIDTH-1:0] wr_data;

wire [DATA_WIDTH-1:0] rd_data;
wire full;
wire empty;

fifo_top #(
    .DATA_WIDTH(DATA_WIDTH),
    .DEPTH(DEPTH),
    .ADDR_WIDTH(ADDR_WIDTH)
) DUT (
    .clk(clk),
    .rst(rst),
    .wr_en(wr_en),
    .rd_en(rd_en),
    .wr_data(wr_data),
    .rd_data(rd_data),
    .full(full),
    .empty(empty)
);

//------------------------------
// Clock Generation
//------------------------------
initial
begin
    clk = 0;
    forever #5 clk = ~clk;
end

//------------------------------
// Reset Generation
//------------------------------
initial
begin
    rst = 1;
    wr_en = 0;
    rd_en = 0;
    wr_data = 0;

    #20;
    rst = 0;
end

//------------------------------
// Write Task
//------------------------------
task write_fifo;
    input [DATA_WIDTH-1:0] data;
begin
    @(posedge clk);

    if (!full)
    begin
        wr_en = 1;
        wr_data = data;
    end

    @(posedge clk);

    wr_en = 0;
    wr_data = 0;
end
endtask

//------------------------------
// Read Task
//------------------------------
task read_fifo;
begin
    @(posedge clk);

    if (!empty)
        rd_en = 1;

    @(posedge clk);

    rd_en = 0;
end
endtask

//------------------------------
// Verification Variables
//------------------------------
integer pass_count;
integer fail_count;
integer i;

reg [DATA_WIDTH-1:0] expected_data;

//------------------------------
// Initialize Verification Variables
//------------------------------
initial
begin
    pass_count = 0;
    fail_count = 0;
    expected_data = 0;
end

//------------------------------
// Main Test Sequence
//------------------------------
initial
begin

    $dumpfile("waveforms/fifo_tb.vcd");
    $dumpvars(0, fifo_tb);

    @(negedge rst);

    $display("====================================");
    $display(" Starting FIFO Directed Test Cases ");
    $display("====================================");

//----------------------------------------------------------
// DT01 : Reset Verification
//----------------------------------------------------------
rst = 1'b1;
wr_en = 1'b0;
rd_en = 1'b0;
wr_data = 8'h00;
#20;
rst = 1'b0;
#20;

//----------------------------------------------------------
// DT02 : Single Write
//----------------------------------------------------------
write_fifo(8'h11);

//----------------------------------------------------------
// DT03 : Single Read
//----------------------------------------------------------
read_fifo();

//----------------------------------------------------------
// DT04 : Multiple Sequential Writes
//----------------------------------------------------------
write_fifo(8'h21);
write_fifo(8'h22);
write_fifo(8'h23);

//----------------------------------------------------------
// DT05 : Multiple Sequential Reads
//----------------------------------------------------------
read_fifo();
read_fifo();
read_fifo();

//----------------------------------------------------------
// DT06 : Alternating Write and Read
//----------------------------------------------------------
write_fifo(8'h31);
read_fifo();

write_fifo(8'h32);
read_fifo();

write_fifo(8'h33);
read_fifo();

//----------------------------------------------------------
// DT07 : Continuous Writes
//----------------------------------------------------------
write_fifo(8'h41);
write_fifo(8'h42);
write_fifo(8'h43);
write_fifo(8'h44);
write_fifo(8'h45);
write_fifo(8'h46);

//----------------------------------------------------------
// DT08 : Continuous Reads
//----------------------------------------------------------
read_fifo();
read_fifo();
read_fifo();
read_fifo();
read_fifo();
read_fifo();

//----------------------------------------------------------
// DT09 : FIFO Full Condition
//----------------------------------------------------------
repeat (DEPTH)
    write_fifo($random);

#20;

//----------------------------------------------------------
// DT10 : Write When FIFO Full (Overflow Check)
//----------------------------------------------------------
write_fifo(8'hAA);

#20;

//----------------------------------------------------------
// DT11 : FIFO Empty Condition
//----------------------------------------------------------
repeat (DEPTH)
    read_fifo();

#20;

//----------------------------------------------------------
// DT12 : Read When FIFO Empty (Underflow Check)
//----------------------------------------------------------
read_fifo();

#20;

//----------------------------------------------------------
// DT13 : Pointer Wrap-around & Mixed Operations
//----------------------------------------------------------
repeat(DEPTH+2)
    write_fifo($random);

repeat(DEPTH/2)
    read_fifo();

repeat(DEPTH/2)
    write_fifo($random);

repeat(DEPTH+2)
    read_fifo();

// Simultaneous Read & Write
@(posedge clk);
wr_en   = 1;
rd_en   = 1;
wr_data = 8'hAA;

@(posedge clk);
wr_en = 0;
rd_en = 0;   

#50;

    $display("========================================");
    $display(" Directed Test Cases Completed ");
    $display("========================================");

    #20;

    $display("====================================");
    $display(" Simulation Completed ");
    $display("====================================");

    $finish;
end

//==========================================================
// CORNER TEST CASES
//==========================================================

initial
begin

$display("========================================");
$display(" Starting FIFO Corner Test Cases ");
$display("========================================");

//----------------------------------------------------------
// CT01 : Reset During Active Operation
//----------------------------------------------------------
$display("CT01 : Reset During Active Operation");

write_fifo(8'h11);
write_fifo(8'h22);

rst = 1;

#20;

rst = 0;

#20;


//----------------------------------------------------------
// CT02 : Fill -> Empty -> Fill Again
//----------------------------------------------------------
$display("CT02 : Fill -> Empty -> Fill Again");

repeat(DEPTH)
    write_fifo($random);

repeat(DEPTH)
    read_fifo();

repeat(DEPTH)
    write_fifo($random);

#20;


//----------------------------------------------------------
// CT03 : Continuous Simultaneous Read & Write
//----------------------------------------------------------
$display("CT03 : Continuous Simultaneous Read & Write");

repeat(8)
begin
    @(posedge clk);
    wr_en   = 1;
    rd_en   = 1;
    wr_data = $random;
end

@(posedge clk);

wr_en = 0;
rd_en = 0;

#20;


//----------------------------------------------------------
// CT04 : Full -> Not Full -> Full Transition
//----------------------------------------------------------
$display("CT04 : Full -> Not Full -> Full");

repeat(DEPTH)
    write_fifo($random);

read_fifo();

write_fifo($random);

#20;


//----------------------------------------------------------
// CT05 : Empty -> Not Empty -> Empty Transition
//----------------------------------------------------------
$display("CT05 : Empty -> Not Empty -> Empty");

write_fifo(8'h77);

read_fifo();

#20;


//----------------------------------------------------------
// CT06 : Long Stress Operation
//----------------------------------------------------------
$display("CT06 : Long Stress Operation");

repeat(50)
begin
    if($random % 2)
        write_fifo($random);
    else
        read_fifo();
end

#20;

$display("========================================");
$display(" Corner Test Cases Completed ");
$display("========================================");

end

//----------------------------------------------------------
// RANDOMIZED STRESS TEST (100 Random Transactions)
//----------------------------------------------------------

initial
begin

$display("========================================");
$display(" Starting Randomized Stress Test ");
$display("========================================");

repeat(100)
begin
    case($random % 4)

        // Random Write
        0:
        begin
            write_fifo($random);
        end

        // Random Read
        1:
        begin
            read_fifo();
        end

        // Simultaneous Read & Write
        2:
        begin
            @(posedge clk);

            if(!full)
            begin
                wr_en   = 1;
                wr_data = $random;
            end

            if(!empty)
                rd_en = 1;

            @(posedge clk);

            wr_en = 0;
            rd_en = 0;
            wr_data = 0;
        end

        // Idle Cycle
        default:
        begin
            @(posedge clk);

            wr_en   = 0;
            rd_en   = 0;
            wr_data = 0;
        end

    endcase
end

#50;

$display("========================================");
$display(" 100 Random Transactions Completed ");
$display("========================================");

end

//------------------------------
// Monitor
//------------------------------
initial
begin
    $monitor("Time=%0t | wr_en=%b rd_en=%b wr_data=%h rd_data=%h full=%b empty=%b",
              $time, wr_en, rd_en, wr_data, rd_data, full, empty);
end

endmodule

waveforms/fifo_tb.vcd
$date
	Sat Jul 04 12:57:47 2026
$end
$version
	Icarus Verilog
$end
$timescale
	1ps
$end
$scope module fifo_tb $end
$var wire 8 ! rd_data [7:0] $end
$var wire 1 " full $end
$var wire 1 # empty $end
$var parameter 32 $ ADDR_WIDTH $end
$var parameter 32 % DATA_WIDTH $end
$var parameter 32 & DEPTH $end
$var reg 1 ' clk $end
$var reg 8 ( expected_data [7:0] $end
$var reg 1 ) rd_en $end
$var reg 1 * rst $end
$var reg 8 + wr_data [7:0] $end
$var reg 1 , wr_en $end
$var integer 32 - fail_count [31:0] $end
$var integer 32 . pass_count [31:0] $end
$scope module DUT $end
$var wire 1 ' clk $end
$var wire 1 ) rd_en $end
$var wire 1 * rst $end
$var wire 8 / wr_data [7:0] $end
$var wire 1 , wr_en $end
$var wire 1 0 write_enable $end
$var wire 4 1 wr_ptr [3:0] $end
$var wire 1 2 read_enable $end
$var wire 4 3 rd_ptr [3:0] $end
$var wire 8 4 rd_data [7:0] $end
$var wire 1 " full $end
$var wire 1 # empty $end
$var wire 5 5 count [4:0] $end
$var parameter 32 6 ADDR_WIDTH $end
$var parameter 32 7 DATA_WIDTH $end
$var parameter 32 8 DEPTH $end
$scope module u_empty_logic $end
$var wire 1 # empty $end
$var wire 5 9 count [4:0] $end
$var parameter 32 : ADDR_WIDTH $end
$upscope $end
$scope module u_fifo_counter $end
$var wire 1 ' clk $end
$var wire 1 # empty $end
$var wire 1 ) rd_en $end
$var wire 1 * rst $end
$var wire 1 , wr_en $end
$var wire 1 " full $end
$var parameter 32 ; ADDR_WIDTH $end
$var parameter 32 < DEPTH $end
$var reg 5 = count [4:0] $end
$upscope $end
$scope module u_fifo_memory $end
$var wire 1 ' clk $end
$var wire 8 > wr_data [7:0] $end
$var wire 4 ? wr_ptr [3:0] $end
$var wire 1 0 wr_en $end
$var wire 4 @ rd_ptr [3:0] $end
$var wire 1 2 rd_en $end
$var parameter 32 A ADDR_WIDTH $end
$var parameter 32 B DATA_WIDTH $end
$var parameter 32 C DEPTH $end
$var reg 8 D rd_data [7:0] $end
$upscope $end
$scope module u_full_logic $end
$var wire 5 E count [4:0] $end
$var wire 1 " full $end
$var parameter 32 F ADDR_WIDTH $end
$var parameter 32 G DEPTH $end
$upscope $end
$scope module u_read_control $end
$var wire 1 # empty $end
$var wire 1 ) rd_en $end
$var wire 1 2 read_enable $end
$upscope $end
$scope module u_read_pointer $end
$var wire 1 ' clk $end
$var wire 1 # empty $end
$var wire 1 2 rd_en $end
$var wire 1 * rst $end
$var parameter 32 H ADDR_WIDTH $end
$var parameter 32 I DEPTH $end
$var parameter 4 J LAST_ADDR $end
$var reg 4 K rd_ptr [3:0] $end
$upscope $end
$scope module u_write_control $end
$var wire 1 " full $end
$var wire 1 , wr_en $end
$var wire 1 0 write_enable $end
$upscope $end
$scope module u_write_pointer $end
$var wire 1 ' clk $end
$var wire 1 " full $end
$var wire 1 * rst $end
$var wire 1 0 wr_en $end
$var parameter 32 L ADDR_WIDTH $end
$var parameter 32 M DEPTH $end
$var parameter 4 N LAST_ADDR $end
$var reg 4 O wr_ptr [3:0] $end
$upscope $end
$upscope $end
$scope task read_fifo $end
$upscope $end
$scope task write_fifo $end
$var reg 8 P data [7:0] $end
$upscope $end
$upscope $end
$enddefinitions $end
$comment Show the parameter values. $end
$dumpall
b1111 N
b10000 M
b100 L
b1111 J
b10000 I
b100 H
b10000 G
b100 F
b10000 C
b1000 B
b100 A
b10000 <
b100 ;
b100 :
b10000 8
b1000 7
b100 6
b10000 &
b1000 %
b100 $
$end
#0
$dumpvars
bx P
b0 O
b0 K
b0 E
bx D
b0 @
b0 ?
b0 >
b0 =
b0 9
b0 5
bx 4
b0 3
02
b0 1
00
b0 /
b0 .
b0 -
0,
b0 +
1*
0)
b0 (
0'
1#
0"
bx !
$end
#5000
1'
#10000
0'
#15000
1'
#20000
0'
1*
#25000
1'
#30000
0'
#35000
1'
#40000
0'
0*
#45000
1'
#50000
0'
#55000
1'
#60000
0'
b10001 P
#65000
0#
b1 5
b1 9
b1 =
b1 E
10
b10001 +
b10001 /
b10001 >
1,
1'
#70000
0'
#75000
b1 1
b1 ?
b1 O
00
b0 +
b0 /
b0 >
0,
1'
#80000
0'
#85000
1#
b0 5
b0 9
b0 =
b0 E
02
1)
1'
#90000
0'
#95000
b100001 P
0)
1'
#100000
0'
#105000
0#
b1 5
b1 9
b1 =
b1 E
10
b100001 +
b100001 /
b100001 >
1,
1'
#110000
0'
#115000
b10 1
b10 ?
b10 O
00
b100010 P
b0 +
b0 /
b0 >
0,
1'
#120000
0'
#125000
b10 5
b10 9
b10 =
b10 E
10
b100010 +
b100010 /
b100010 >
1,
1'
#130000
0'
#135000
b11 1
b11 ?
b11 O
00
b100011 P
b0 +
b0 /
b0 >
0,
1'
#140000
0'
#145000
b11 5
b11 9
b11 =
b11 E
10
b100011 +
b100011 /
b100011 >
1,
1'
#150000
0'
#155000
b100 1
b100 ?
b100 O
00
b0 +
b0 /
b0 >
0,
1'
#160000
0'
#165000
b10 5
b10 9
b10 =
b10 E
12
1)
1'
#170000
0'
#175000
b1 3
b1 @
b1 K
b10001 !
b10001 4
b10001 D
02
0)
1'
#180000
0'
#185000
b1 5
b1 9
b1 =
b1 E
12
1)
1'
#190000
0'
#195000
b10 3
b10 @
b10 K
b100001 !
b100001 4
b100001 D
02
0)
1'
#200000
0'
#205000
1#
b0 5
b0 9
b0 =
b0 E
02
1)
1'
#210000
0'
#215000
b110001 P
0)
1'
#220000
0'
#225000
0#
b1 5
b1 9
b1 =
b1 E
10
b110001 +
b110001 /
b110001 >
1,
1'
#230000
0'
#235000
b101 1
b101 ?
b101 O
00
b0 +
b0 /
b0 >
0,
1'
#240000
0'
#245000
1#
b0 5
b0 9
b0 =
b0 E
02
1)
1'
#250000
0'
#255000
b110010 P
0)
1'
#260000
0'
#265000
0#
b1 5
b1 9
b1 =
b1 E
10
b110010 +
b110010 /
b110010 >
1,
1'
#270000
0'
#275000
b110 1
b110 ?
b110 O
00
b0 +
b0 /
b0 >
0,
1'
#280000
0'
#285000
1#
b0 5
b0 9
b0 =
b0 E
02
1)
1'
#290000
0'
#295000
b110011 P
0)
1'
#300000
0'
#305000
0#
b1 5
b1 9
b1 =
b1 E
10
b110011 +
b110011 /
b110011 >
1,
1'
#310000
0'
#315000
b111 1
b111 ?
b111 O
00
b0 +
b0 /
b0 >
0,
1'
#320000
0'
#325000
1#
b0 5
b0 9
b0 =
b0 E
02
1)
1'
#330000
0'
#335000
b1000001 P
0)
1'
#340000
0'
#345000
0#
b1 5
b1 9
b1 =
b1 E
10
b1000001 +
b1000001 /
b1000001 >
1,
1'
#350000
0'
#355000
b1000 1
b1000 ?
b1000 O
00
b1000010 P
b0 +
b0 /
b0 >
0,
1'
#360000
0'
#365000
b10 5
b10 9
b10 =
b10 E
10
b1000010 +
b1000010 /
b1000010 >
1,
1'
#370000
0'
#375000
b1001 1
b1001 ?
b1001 O
00
b1000011 P
b0 +
b0 /
b0 >
0,
1'
#380000
0'
#385000
b11 5
b11 9
b11 =
b11 E
10
b1000011 +
b1000011 /
b1000011 >
1,
1'
#390000
0'
#395000
b1010 1
b1010 ?
b1010 O
00
b1000100 P
b0 +
b0 /
b0 >
0,
1'
#400000
0'
#405000
b100 5
b100 9
b100 =
b100 E
10
b1000100 +
b1000100 /
b1000100 >
1,
1'
#410000
0'
#415000
b1011 1
b1011 ?
b1011 O
00
b1000101 P
b0 +
b0 /
b0 >
0,
1'
#420000
0'
#425000
b101 5
b101 9
b101 =
b101 E
10
b1000101 +
b1000101 /
b1000101 >
1,
1'
#430000
0'
#435000
b1100 1
b1100 ?
b1100 O
00
b1000110 P
b0 +
b0 /
b0 >
0,
1'
#440000
0'
#445000
b110 5
b110 9
b110 =
b110 E
10
b1000110 +
b1000110 /
b1000110 >
1,
1'
#450000
0'
#455000
b1101 1
b1101 ?
b1101 O
00
b0 +
b0 /
b0 >
0,
1'
#460000
0'
#465000
b101 5
b101 9
b101 =
b101 E
12
1)
1'
#470000
0'
#475000
b11 3
b11 @
b11 K
b100010 !
b100010 4
b100010 D
02
0)
1'
#480000
0'
#485000
b100 5
b100 9
b100 =
b100 E
12
1)
1'
#490000
0'
#495000
b100 3
b100 @
b100 K
b100011 !
b100011 4
b100011 D
02
0)
1'
#500000
0'
#505000
b11 5
b11 9
b11 =
b11 E
12
1)
1'
#510000
0'
#515000
b101 3
b101 @
b101 K
b110001 !
b110001 4
b110001 D
02
0)
1'
#520000
0'
#525000
b10 5
b10 9
b10 =
b10 E
12
1)
1'
#530000
0'
#535000
b110 3
b110 @
b110 K
b110010 !
b110010 4
b110010 D
02
0)
1'
#540000
0'
#545000
b1 5
b1 9
b1 =
b1 E
12
1)
1'
#550000
0'
#555000
b111 3
b111 @
b111 K
b110011 !
b110011 4
b110011 D
02
0)
1'
#560000
0'
#565000
1#
b0 5
b0 9
b0 =
b0 E
02
1)
1'
#570000
0'
#575000
b100100 P
0)
1'
#580000
0'
#585000
0#
b1 5
b1 9
b1 =
b1 E
10
b100100 +
b100100 /
b100100 >
1,
1'
#590000
0'
#595000
b1110 1
b1110 ?
b1110 O
00
b10000001 P
b0 +
b0 /
b0 >
0,
1'
#600000
0'
#605000
b10 5
b10 9
b10 =
b10 E
10
b10000001 +
b10000001 /
b10000001 >
1,
1'
#610000
0'
#615000
b1111 1
b1111 ?
b1111 O
00
b1001 P
b0 +
b0 /
b0 >
0,
1'
#620000
0'
#625000
b11 5
b11 9
b11 =
b11 E
10
b1001 +
b1001 /
b1001 >
1,
1'
#630000
0'
#635000
b0 1
b0 ?
b0 O
00
b1100011 P
b0 +
b0 /
b0 >
0,
1'
#640000
0'
#645000
b100 5
b100 9
b100 =
b100 E
10
b1100011 +
b1100011 /
b1100011 >
1,
1'
#650000
0'
#655000
b1 1
b1 ?
b1 O
00
b1101 P
b0 +
b0 /
b0 >
0,
1'
#660000
0'
#665000
b101 5
b101 9
b101 =
b101 E
10
b1101 +
b1101 /
b1101 >
1,
1'
#670000
0'
#675000
b10 1
b10 ?
b10 O
00
b10001101 P
b0 +
b0 /
b0 >
0,
1'
#680000
0'
#685000
b110 5
b110 9
b110 =
b110 E
10
b10001101 +
b10001101 /
b10001101 >
1,
1'
#690000
0'
#695000
b11 1
b11 ?
b11 O
00
b1100101 P
b0 +
b0 /
b0 >
0,
1'
#700000
0'
#705000
b111 5
b111 9
b111 =
b111 E
10
b1100101 +
b1100101 /
b1100101 >
1,
1'
#710000
0'
#715000
b100 1
b100 ?
b100 O
00
b10010 P
b0 +
b0 /
b0 >
0,
1'
#720000
0'
#725000
b1000 5
b1000 9
b1000 =
b1000 E
10
b10010 +
b10010 /
b10010 >
1,
1'
#730000
0'
#735000
b101 1
b101 ?
b101 O
00
b1 P
b0 +
b0 /
b0 >
0,
1'
#740000
0'
#745000
b1001 5
b1001 9
b1001 =
b1001 E
10
b1 +
b1 /
b1 >
1,
1'
#750000
0'
#755000
b110 1
b110 ?
b110 O
00
b1101 P
b0 +
b0 /
b0 >
0,
1'
#760000
0'
#765000
b1010 5
b1010 9
b1010 =
b1010 E
10
b1101 +
b1101 /
b1101 >
1,
1'
#770000
0'
#775000
b111 1
b111 ?
b111 O
00
b1110110 P
b0 +
b0 /
b0 >
0,
1'
#780000
0'
#785000
b1011 5
b1011 9
b1011 =
b1011 E
10
b1110110 +
b1110110 /
b1110110 >
1,
1'
#790000
0'
#795000
b1000 1
b1000 ?
b1000 O
00
b111101 P
b0 +
b0 /
b0 >
0,
1'
#800000
0'
#805000
b1100 5
b1100 9
b1100 =
b1100 E
10
b111101 +
b111101 /
b111101 >
1,
1'
#810000
0'
#815000
b1001 1
b1001 ?
b1001 O
00
b11101101 P
b0 +
b0 /
b0 >
0,
1'
#820000
0'
#825000
b1101 5
b1101 9
b1101 =
b1101 E
10
b11101101 +
b11101101 /
b11101101 >
1,
1'
#830000
0'
#835000
b1010 1
b1010 ?
b1010 O
00
b10001100 P
b0 +
b0 /
b0 >
0,
1'
#840000
0'
#845000
b1110 5
b1110 9
b1110 =
b1110 E
10
b10001100 +
b10001100 /
b10001100 >
1,
1'
#850000
0'
#855000
b1011 1
b1011 ?
b1011 O
00
b11111001 P
b0 +
b0 /
b0 >
0,
1'
#860000
0'
#865000
b1111 5
b1111 9
b1111 =
b1111 E
10
b11111001 +
b11111001 /
b11111001 >
1,
1'
#870000
0'
#875000
b1100 1
b1100 ?
b1100 O
00
b11000110 P
b0 +
b0 /
b0 >
0,
1'
#880000
0'
#885000
1"
b10000 5
b10000 9
b10000 =
b10000 E
00
b11000110 +
b11000110 /
b11000110 >
1,
1'
#890000
0'
#895000
b0 +
b0 /
b0 >
0,
1'
#900000
0'
#905000
1'
#910000
0'
#915000
1'
b10101010 P
#920000
0'
#925000
1'
#930000
0'
#935000
1'
#940000
0'
#945000
0"
b1111 5
b1111 9
b1111 =
b1111 E
12
1)
1'
#950000
0'
#955000
b1000 3
b1000 @
b1000 K
b1110110 !
b1110110 4
b1110110 D
02
0)
1'
#960000
0'
#965000
b1110 5
b1110 9
b1110 =
b1110 E
12
1)
1'
#970000
0'
#975000
b1001 3
b1001 @
b1001 K
b111101 !
b111101 4
b111101 D
02
0)
1'
#980000
0'
#985000
b1101 5
b1101 9
b1101 =
b1101 E
12
1)
1'
#990000
0'
#995000
b1010 3
b1010 @
b1010 K
b11101101 !
b11101101 4
b11101101 D
02
0)
1'
#1000000
0'
#1005000
b1100 5
b1100 9
b1100 =
b1100 E
12
1)
1'
#1010000
0'
#1015000
b1011 3
b1011 @
b1011 K
b10001100 !
b10001100 4
b10001100 D
02
0)
1'
#1020000
0'
#1025000
b1011 5
b1011 9
b1011 =
b1011 E
12
1)
1'
#1030000
0'
#1035000
b1100 3
b1100 @
b1100 K
b11111001 !
b11111001 4
b11111001 D
02
0)
1'
#1040000
0'
#1045000
b1010 5
b1010 9
b1010 =
b1010 E
12
1)
1'
#1050000
0'
#1055000
b1101 3
b1101 @
b1101 K
b1000110 !
b1000110 4
b1000110 D
02
0)
1'
#1060000
0'
#1065000
b1001 5
b1001 9
b1001 =
b1001 E
12
1)
1'
#1070000
0'
#1075000
b1110 3
b1110 @
b1110 K
b100100 !
b100100 4
b100100 D
02
0)
1'
#1080000
0'
#1085000
b1000 5
b1000 9
b1000 =
b1000 E
12
1)
1'
#1090000
0'
#1095000
b1111 3
b1111 @
b1111 K
b10000001 !
b10000001 4
b10000001 D
02
0)
1'
#1100000
0'
#1105000
b111 5
b111 9
b111 =
b111 E
12
1)
1'
#1110000
0'
#1115000
b0 3
b0 @
b0 K
b1001 !
b1001 4
b1001 D
02
0)
1'
#1120000
0'
#1125000
b110 5
b110 9
b110 =
b110 E
12
1)
1'
#1130000
0'
#1135000
b1 3
b1 @
b1 K
b1100011 !
b1100011 4
b1100011 D
02
0)
1'
#1140000
0'
#1145000
b101 5
b101 9
b101 =
b101 E
12
1)
1'
#1150000
0'
#1155000
b10 3
b10 @
b10 K
b1101 !
b1101 4
b1101 D
02
0)
1'
#1160000
0'
#1165000
b100 5
b100 9
b100 =
b100 E
12
1)
1'
#1170000
0'
#1175000
b11 3
b11 @
b11 K
b10001101 !
b10001101 4
b10001101 D
02
0)
1'
#1180000
0'
#1185000
b11 5
b11 9
b11 =
b11 E
12
1)
1'
#1190000
0'
#1195000
b100 3
b100 @
b100 K
b1100101 !
b1100101 4
b1100101 D
02
0)
1'
#1200000
0'
#1205000
b10 5
b10 9
b10 =
b10 E
12
1)
1'
#1210000
0'
#1215000
b101 3
b101 @
b101 K
b10010 !
b10010 4
b10010 D
02
0)
1'
#1220000
0'
#1225000
b1 5
b1 9
b1 =
b1 E
12
1)
1'
#1230000
0'
#1235000
b110 3
b110 @
b110 K
b1 !
b1 4
b1 D
02
0)
1'
#1240000
0'
#1245000
1#
b0 5
b0 9
b0 =
b0 E
02
1)
1'
#1250000
0'
#1255000
0)
1'
#1260000
0'
#1265000
1'
#1270000
0'
#1275000
1'
#1280000
0'
#1285000
1'
#1290000
0'
#1295000
1'
#1300000
0'
#1305000
0#
b1 5
b1 9
b1 =
b1 E
10
b11000101 +
b11000101 /
b11000101 >
1,
1'
b11000101 P
#1310000
0'
#1315000
b1101 1
b1101 ?
b1101 O
00
b10101010 P
b0 +
b0 /
b0 >
0,
1'
#1320000
0'
#1325000
b10 5
b10 9
b10 =
b10 E
10
b10101010 +
b10101010 /
b10101010 >
1,
1'
#1330000
0'
#1335000
b1110 1
b1110 ?
b1110 O
00
b11100101 P
b0 +
b0 /
b0 >
0,
1'
#1340000
0'
#1345000
b11 5
b11 9
b11 =
b11 E
10
b11100101 +
b11100101 /
b11100101 >
1,
1'
#1350000
0'
#1355000
b1111 1
b1111 ?
b1111 O
00
b1110111 P
b0 +
b0 /
b0 >
0,
1'
#1360000
0'
#1365000
b100 5
b100 9
b100 =
b100 E
10
b1110111 +
b1110111 /
b1110111 >
1,
1'
#1370000
0'
#1375000
b0 1
b0 ?
b0 O
00
b10010 P
b0 +
b0 /
b0 >
0,
1'
#1380000
0'
#1385000
b101 5
b101 9
b101 =
b101 E
10
b10010 +
b10010 /
b10010 >
1,
1'
#1390000
0'
#1395000
b1 1
b1 ?
b1 O
00
b10001111 P
b0 +
b0 /
b0 >
0,
1'
#1400000
0'
#1405000
b110 5
b110 9
b110 =
b110 E
10
b10001111 +
b10001111 /
b10001111 >
1,
1'
#1410000
0'
#1415000
b10 1
b10 ?
b10 O
00
b11110010 P
b0 +
b0 /
b0 >
0,
1'
#1420000
0'
#1425000
b111 5
b111 9
b111 =
b111 E
10
b11110010 +
b11110010 /
b11110010 >
1,
1'
#1430000
0'
